Workbook

Sheet 00 ReadMe
A1: دليل ملف التقييم الاقتصادي لمساهمة أ. وسام وهيكل الشراكة
A2: الغرض | B2: توضيح منهجية التقييم الاقتصادي لمساهمة أ. وسام غير النقدية، وربطها بالتمويل النقدي للمستثمر للوصول إلى مؤشر اقتصادي مرجعي لهيكل الشراكة.
A3: قاعدة العمل | B3: لا يتم احتساب نسبة الشراكة قبل تثبيت المدخلات المالية الرئيسية، وتحديد الأصول/الحقوق التي يقدمها المؤسس، وفصل الخدمات المستقبلية عن الأصول الحالية.
A4: المدخلات | B4: البيانات المالية والفنية والسوقية والأدلة الداعمة للملكية الفكرية والـKnow-how.
A5: الافتراضات التقييمية | B5: تظهر بصورة مستقلة عن البيانات المعتمدة، ويجري اختبار أثرها من خلال سيناريوهات Low / Base / High.
A6: النتائج المحسوبة | B6: تنتج تلقائياً من معادلات التقييم ولا تمثل نسبة شراكة ملزمة قبل اتفاق الأطراف.
A7: ملاحظة | B7: السيناريو Base هو المرجع الاقتصادي الحالي، بينما Low وHigh يمثلان اختبار حساسية لقيمة المساهمة غير النقدية.
A9: ترتيب العمل | B9: 1) تثبيت النموذج المالي | C9: 2) حصر IP/Know-how | D9: 3) تقييم المساهمات | E9: 4) منع الازدواج | F9: 5) مقارنة المستثمر | G9: 6) سيناريوهات الحصص | H9: 7) التوصية
A10: بيانات أساسية مطلوبة وفق معايير التقييم (IVS)
A11: أساس القيمة (Basis of Value) | B11: القيمة السوقية العادلة (Fair Market Value) بين طرفين راغبين، غير مضطرين، ولديهما معرفة معقولة بالحقائق — الأساس المعتاد لتقييم حصة عينية بين شركاء.
A12: تاريخ التقييم (Valuation Date) | B12: جميع الأرقام والتوقعات مبنية على المعلومات المتاحة حتى هذا التاريخ - 12 أغسطس 2026
A13: الغرض من التقييم (Purpose) | B13: دعم مفاوضات تحديد نسب الشراكة بين الشريك المؤسس والشريك الممول عند تأسيس الشركة. لا يُستخدم لأي غرض آخر (كالتقاضي أو التقارير المالية المدققة) دون مراجعة مستقلة.
A14: طبيعة التقرير | B14: أُعد هذا التقرير كتحليل اقتصادي استشاري مستقل لدعم التفاوض واتخاذ القرار بين أ. وسام والمستثمر.
A15: حدود الاستخدام | B15: هذا التحليل الاقتصادي لا يُعد تقرير تقييم نظامي معتمداً لأغراض التقاضي أو التقارير المالية المدققة، ولا يغني عن التوثيق القانوني لحقوق الملكية الفكرية وعقد الشراكة.
A17: استكمال بيانات وسام
A18: راجع شيت «07 استكمال بيانات وسام» للبنود التي يعبئها/يدعمها وسام قبل اعتماد التقييم النهائي. الخانات الصفراء هي المطلوب استكماله عند توفره.

Sheet 00b دليل الأرقام للعميل
A1: مرجعية البيانات والافتراضات المستخدمة في التقييم
A2: تعرض هذه الصفحة أهم البيانات والافتراضات التي بُني عليها التقييم، مع توضيح مرجعيتها وحالة اعتمادها.
A3: البند | B3: القيمة / الافتراض | C3: المرجعية | D3: حالة الاعتماد
A4: إجمالي التمويل النقدي المطلوب | B4: 5,535,983 ريال | C4: الدراسة المالية المعتمدة | D4: معتمد
A5: سعر البيع | B5: 62 ريال/م² | C5: الدراسة المالية المعتمدة | D5: معتمد
A6: الطاقة الإنتاجية الأساسية | B6: 249,600 م² سنوياً | C6: الدراسة المالية المعتمدة | D6: معتمد
A7: تكلفة خط الإنتاج | B7: 2,062,500 ريال | C7: الدراسة المالية المعتمدة | D7: معتمد
A8: المعدات الصناعية | B8: 375,000 ريال | C8: الدراسة المالية المعتمدة | D8: معتمد
A9: الإيرادات – السنة الأولى | B9: 15,475,200 ريال | C9: ناتج السعر × الطاقة الأساسية | D9: محسوب
A10: ملكية الشهادة السعودية | B10: أ. وسام | C10: شهادة الحماية السعودية | D10: موثق
A11: الخلطة والـKnow-how | B11: مملوكة لأ. وسام | C11: أساس التقييم والأدلة الفنية | D11: معتمد كأساس للتقييم
A12: تصميم وتطوير خط الإنتاج | B12: مملوك لأ. وسام | C12: الدراسة والأدلة الفنية | D12: معتمد كأساس للتقييم
A13: Royalty Rate | B13: وفق سيناريوهات Low / Base / High | C13: Benchmarks لاتفاقيات ترخيص منشورة | D13: افتراض تقييمي
A14: معدل الخصم | B14: وفق سيناريوهات التقييم | C14: تحليل مخاطر المشروع | D14: افتراض تقييمي
... A16: عامل تحقق التحول التجاري | B16: 45% / 60% / 75% (Low/Base/High) | C16: افتراض تقييمي لأركان لمرحلة ما قبل التشغيل | D16: افتراض تقييمي
A17: قيمة مساهمة أ. وسام – Base | B17: ='04 Founder Contribution'!C25 -> 1578348.3 | C17: ناتج نموذج التقييم | D17: ناتج محسوب
A18: مساهمة المستثمر النقدية | B18: 5,535,983 ريال | C18: التمويل المطلوب للمشروع | D18: معتمد
A19: مؤشر ملكية أ. وسام – Base | B19: ='05 Partnership Structure'!E20 -> 0.22185477 | C19: مقارنة القيمة العينية بالتمويل النقدي | D19: مؤشر اقتصادي
A20: مؤشر ملكية المستثمر – Base | B20: ='05 Partnership Structure'!F20 -> 0.77814523 | C20: مقارنة التمويل النقدي بالقيمة الإجمالية | D20: مؤشر اقتصادي
A22: ملاحظة منهجية | B22: لا تُضاف الخبرة أو التطوير الهندسي مرة ثانية إذا كانت منفعتها محسوبة بالفعل ضمن قيمة الـIP/Know-how. | C22: منع Double Counting | D22: قاعدة تقييم
A23: بيانات الاستكمال | B23: أي مستندات أو تكاليف فعلية إضافية يقدمها أ. وسام تتم مراجعتها أولاً قبل تعديل التقييم. | C23: راجع شيت «07 استكمال بيانات وسام» | D23: للاستكمال

Sheet 00c التوافق مع معايير التقييم
A1: الإطار المهني ومنهجية التقييم
A2: أعدت أركان هذا التحليل الاقتصادي الاستشاري لتقدير المساهمة غير النقدية لأ. وسام ودعم مفاوضات هيكل الشراكة. وروعي في بناء النموذج استخدام مداخل تقييم الأصول غير الملموسة بما يتناسب مع طبيعة الأصل والبيانات المتاحة.
A4: العنصر | B4: المعالجة في التقرير | C4: الغرض | D4: الحالة
A5: الغرض من التقييم | B5: دعم التفاوض حول هيكل الشراكة | C5: تقدير القيمة الاقتصادية للمساهمة غير النقدية | D5: معتمد
A6: محل التقييم | B6: IP + Know-how + التطوير الفني والهندسي | C6: تحديد العناصر التي تمثل مساهمة أ. وسام | D6: معتمد
A7: Cost Approach | B7: مستخدم كـ Cross-check | C7: اختبار تكلفة إعادة إنشاء/استبدال عناصر التطوير | D7: منهج داعم
A8: Income Approach | B8: المنهج الرئيسي – Relief from Royalty | C8: قياس المنفعة الاقتصادية المرتبطة بامتلاك/استخدام التقنية والحقوق | D8: منهج رئيسي
A9: Market Evidence | B9: مقارنات وBenchmarks داعمة | C9: دعم افتراضات التقييم ومعدلات الترخيص | D9: دليل داعم
A10: مخاطر ما قبل التشغيل | B10: عامل تحقق تجاري ضمن Income Approach | C10: فصل قيمة التقنية الحالية عن القيمة التي تتطلب تمويل المستثمر والتنفيذ التجاري | D10: مطبق
A11: السيناريو المرجعي | B11: Base | C11: المرجع الاقتصادي المستخدم في قراءة النتيجة | D11: مرجعي
A12: سيناريوهات Low / High | B12: اختبار حساسية | C12: قياس أثر تغير الافتراضات وقوة الأدلة | D12: ليست نسباً ملزمة
A13: طبيعة النتيجة | B13: مؤشر اقتصادي استشاري للتفاوض | C13: دعم اتخاذ القرار بين الأطراف | D13: غير ملزم تعاقدياً
A14: طبيعة التقرير
A15: يمثل هذا التقرير تحليلاً اقتصادياً استشارياً أعدته أركان لدعم اتخاذ القرار والتفاوض بين الأطراف، ولا يمثل تقرير تقييم نظامي صادراً عن مقيّم معتمد متى كان ذلك مطلوباً نظاماً لغرض محدد.
A17: ملاحظة بشأن النتيجة
A18: السيناريو Base هو المرجع الاقتصادي الحالي. أما Low وHigh فيستخدمان لاختبار حساسية قيمة المساهمة غير النقدية، ولا يمثل أي منهما نسبة شراكة واجبة أو عرضاً تفاوضياً ملزماً.

Sheet 01 Stage1 Normalization
A1: المرحلة الأولى – مراجعة وتوحيد المدخلات المالية
A2: البند | B2: القيمة الحالية | C2: قيمة متعارضة | D2: القيمة المعتمدة | E2: الوحدة | F2: حالة المراجعة | G2: المصدر/الملاحظة
A3: إجمالي تكلفة المشروع | B3: 5535983 | D3: 5535983 | E3: ريال | F3: معتمد | G3: الدراسة المالية المعتمدة – ص8: إجمالي رأس المال المطلوب 5,535,983 ريال
A4: الأصول الثابتة | B4: 4316500 | D4: 4316500 | E4: ريال | F4: معتمد | G4: الدراسة المالية المعتمدة – ص4: إجمالي الأصول/التكاليف الرأسمالية 4,316,500 ريال
A5: مصروفات التأسيس | B5: 200250 | D5: 200250 | E5: ريال | F5: معتمد | G5: الدراسة المالية المعتمدة – ص3: مصروفات التأسيس وما قبل التشغيل 200,250 ريال
A6: رأس المال العامل | B6: 1219483 | D6: 1219483 | E6: ريال | F6: معتمد | G6: الدراسة المالية المعتمدة – ص7-8: احتياج تشغيل 941,766 + عمومي وإداري 277,717 = 1,219,483 ريال
A7: سعر البيع للمتر | B7: 62 | D7: 62 | E7: ريال/م² | F7: معتمد | G7: الدراسة المالية المعتمدة – ص9: سعر بيع المتر 62 ريال
A8: الطاقة السنوية القصوى | B8: 249600 | D8: 249600 | E8: م²/سنة | F8: معتمد | G8: الدراسة المالية المعتمدة – ص9: 40 م²/ساعة - 800 م²/يوم - 20,800 م²/شهر - 249,600 م²/سنة
A9: تكلفة خط الإنتاج | B9: 2062500 | D9: 2062500 | E9: ريال | F9: معتمد | G9: الدراسة المالية المعتمدة – ص3: خط إنتاج متكامل 2,062,500 ريال
A10: معدات وأدوات صناعية | B10: 375000 | D10: 375000 | E10: ريال | F10: معتمد | G10: الدراسة المالية المعتمدة – ص3: معدات وأدوات صناعية مختلفة 375,000 ريال
A11: صالة الإنتاج - المساحة | B11: 2500 | D11: 2500 | E11: م² | F11: معتمد | G11: الدراسة المالية المعتمدة – ص3: صالة إنتاج 2,500 م²
A12: صالة الإنتاج - التكلفة | B12: 700000 | D12: 700000 | E12: ريال | F12: معتمد | G12: الدراسة المالية المعتمدة – ص3: تكلفة صالة الإنتاج 700,000 ريال
A14: افتراضات التشغيل – تُثبت قبل التقييم
A15: السنة | B15: 1 | C15: 2 | D15: 3 | E15: 4 | F15: 5 | G15: ملاحظة
A16: نسبة التشغيل | B16: 1 | C16: 1.1 | D16: 1.21 | E16: 1.331 | F16: 1.4641 | G16: مؤشر نمو كمية الإنتاج 10% سنويًا وفق ملاحظة الدراسة المالية : السنة 1 = الطاقة الواردة 249,600 م²
A17: سعر البيع (ريال/م²) | B17: 62 | C17: 62 | D17: 62 | E17: 62 | F17: 62 | G17: سعر البيع المعتمد من الدراسة المالية
A18: الإيرادات السنوية | B18: 15475200 | C18: 17022720 | D18: 18724992 | E18: 20597491 | F18: 22657240 | G18: السنة 1 = 249,600 × 62 - السنوات التالية +10% كمية وفق ملاحظة الدراسة
A19: تنبيه | B19: الطاقة الواردة في الدراسة المالية = 249,600 م²/سنة | G19: أي نمو يتجاوزها يفترض توسعًا/رفع تشغيل ويجب تأكيده فنيًا قبل اعتماد السيناريو النهائي
A21: ملحوظة | B21: هذه الورقة ليست إعادة دراسة جدوى كاملة : هدفها تثبيت المدخلات التي تؤثر مباشرة على التقييم ونسبة الشراكة.

Sheet 02 IP Inventory
A1: المرحلة الثانية (أ) – حصر الملكية الفكرية والمعرفة الفنية
A3: الأصل/المساهمة | B3: النوع | C3: المالك الحالي | D3: التسجيل | E3: الدولة | F3: المدة | G3: قابل للنقل؟ | H3: دليل الملكية | I3: منفعة اقتصادية مستقلة؟ | J3: ملاحظات
A4: ألواح زخرفية للبناء | B4: نموذج صناعي | C4: وسام حسين سعدة | D4: SA 19365 | E4: السعودية | F4: 15 سنة من تاريخ الإيداع | G4: نعم | H4: شهادة SAIP | I4: نعم/جزئي | J4: ملكية وسام معتمدة ضمن نطاق التقييم - يحدد هيكل النقل للشركة (ملكية/ترخيص)
A5: حماية/تسجيل ترفنتينو | B5: تسجيل/حماية | C5: وسام / WESAM SADA | D5: 2024 007051 | E5: تركيا | F5: يحتاج مستند | G5: نعم | H5: الشهادة التركية مطلوبة | I5: نعم/جزئي | J5: ملكية وسام معتمدة ضمن نطاق التقييم - يستخدم التسجيل كمرجع فني/سوقي فقط بعد مطابقة المستند.
A6: الخلطة الصناعية | B6: Know-how / سر فني | C6: وسام حسين سعدة | D6: غير واضح | E6: — | F6: غير محدد | G6: نعم | H6: السيرة المهنية + وصف الخبرات + وصف الابتكار + وصف الدراسة الفنية | I6: نعم إذا محددة | J6: ملكية وسام معتمدة - السيرة المهنية تدعم تراكم الخبرة العملية في الحجر الصناعي والقوالب وتستخدم كدليل داعم للـKnow-how لا كقيمة مستقلة
A7: طريقة التصنيع وضبط الجودة | B7: Know-how | C7: وسام حسين سعدة | D7: غير واضح | E7: — | F7: غير محدد | G7: نعم | H7: SOP/مستندات فنية | I7: جزئي | J7: ملكية وسام معتمدة - تُقيّم فقط بقدر المنفعة القابلة للفصل والنقل.
A8: القوالب/التصميمات الأصلية | B8: تصميم/أصل فني | C8: وسام حسين سعدة | D8: غير واضح | E8: — | F8: غير محدد | G8: نعم | H8: رسومات/فواتير | I8: حسب الحالة | J8: ملكية وسام معتمدة - فصل قيمة القالب المادي عن حقوق التصميم.
A9: تصميمات الماكينات والتعديلات الهندسية | B9: Engineering Design / Know-how | C9: وسام حسين سعدة | D9: غير واضح | E9: — | F9: العمر الاقتصادي للتصميم | G9: نعم | H9: الدراسة الفنية + السيرة المهنية (تنسب تصميم الخط الصناعي المؤتمت للمشروع) + CAD/Drawings عند توفرها | I9: نعم إذا ثبت أنها تطوير خاص | J9: ملكية وسام معتمدة - السيرة المهنية تعزز إسناد التطوير الهندسي والخط المؤتمت لوسام.
A10: تطوير/تهيئة خط الإنتاج | B10: Technical Development | C10: وسام حسين سعدة | D10: غير مسجل كحق مستقل | E10: — | F10: العمر الاقتصادي للخط/التطوير | G10: نعم | H10: الدراسة الفنية + السيرة المهنية + مخططات/أوامر تعديل عند توفرها | I10: نعم إذا نتج عنه خفض تكلفة أو رفع إنتاجية | J10: ملكية وسام معتمدة - الملف المهني يدعم خبرته المباشرة في الحجر الصناعي وتصنيع القوالب ويقوي عامل الإثبات دون Double Counting.
A11: الإشراف الفني السابق على تطوير الآلات | B11: Founder Technical Contribution | C11: وسام حسين سعدة | D11: غير مسجل | E11: — | F11: حتى تاريخ التقييم | G11: لا ينقل كحق بذاته | H11: ساعات موثقة + مهام + مخرجات + معدل سوقي | I11: جزئي | J11: مساهمة سابقة لوسام - تُحتسب فقط إذا لم تكن منفعتها محتسبة ضمن التصميم/Know-how.

Sheet 03 IP Valuation
A1: المرحلة الثانية (ب) – تقييم الملكية الفكرية والـ Know-how
A3: 1) Cost Approach – تكلفة الاستبدال/إعادة التطوير
A4: البند | B4: تاريخي | C4: تقدير استرشادي / Benchmark | D4: نسبة اعتماد حالية | E4: خصم تقادم | F4: قيمة معترف بها حاليًا | G4: حالة الإثبات | H4: الدليل
A5: تطوير الخلطة والتجارب | B5: 0 | C5: 35000 | D5: 0 | E5: 0 | F5: =C5*D5*(1-E5) -> 0 | G5: يحتاج مستند داعم | H5: فواتير/سجلات
A6: النماذج الأولية | B6: 0 | C6: 15000 | D6: 0 | E6: 0 | F6: =C6*D6*(1-E6) -> 0 | G6: يحتاج مستند داعم | H6: فواتير/صور
A7: القوالب والتصميم | B7: 0 | C7: 40000 | D7: 0 | E7: 0 | F7: =C7*D7*(1-E7) -> 0 | G7: يحتاج مستند داعم | H7: فواتير/رسومات
A8: اختبارات وشهادات | B8: 0 | C8: 6000 | D8: 0 | E8: 0 | F8: =C8*D8*(1-E8) -> 0 | G8: يحتاج مستند داعم | H8: تقارير اختبار
A9: رسوم حماية سعودية | B9: 0 | C9: 7500 | D9: 0 | E9: 0 | F9: =C9*D9*(1-E9) -> 0 | G9: ملكية الحق موثقة؛ التكلفة تحتاج إثبات | H9: SAIP
A10: رسوم حماية تركية | B10: 0 | C10: 18000 | D10: 0 | E10: 0 | F10: =C10*D10*(1-E10) -> 0 | G10: يحتاج مستند داعم | H10: التسجيل التركي
A11: تصميمات الماكينات والتعديلات الهندسية | B11: 0 | C11: 412500 | D11: 1 | E11: 0 | F11: =C11*D11*(1-E11) -> 412500 | G11: Benchmark هندسي استرشادي – ليس تكلفة فعلية مثبتة | H11: 20% × تكلفة خط الإنتاج 2,062,500 ريال؛ يستخدم كـCross-check فقط
A12: وقت المؤسس الفني السابق | B12: 0 | C12: 45000 | D12: 0 | E12: 0 | F12: =C12*D12*(1-E12) -> 0 | G12: غير معتمد ضمن قيمة الـIP الحالية | H12: لا يُحتسب دون سجل ساعات/معدل سوقي، ولتجنب تداخل محتمل مع الـKnow-how
A13: قيمة Cost Approach | F13: =SUM(F5:F12) -> 412500
A14: تنبيه مهني: البنود غير المثبتة لا تدخل في القيمة المعترف بها حاليًا. تقدير التطوير الهندسي Benchmark استرشادي لا يمثل تكلفة فعلية دفعها أ. وسام، ويستخدم فقط كاختبار تكلفة داعم.
A15: 2) Income Approach – Relief from Royalty
A16: المدخل | B16: Low | C16: Base | D16: High | E16: الوحدة | F16: المصدر/المطلوب | G16: ملاحظة
A17: Royalty Rate | B17: 0.03 | C17: 0.04 | D17: 0.05 | E17: % | F17: SEC license comparables: 3%-5% of Net Sales | G17: Benchmark bundle: patent/design + know-how/technology; cross-industry, not stone-specific
A18: Discount Rate | B18: 0.22 | C18: 0.2 | D18: 0.18 | E18: % | F18: تقدير مخاطر أصل تقني مبكر/مشروع قبل التشغيل | G18: Low 22% / Base 20% / High 18% — افتراض تقييم وليس معدل سوق مباشر
A19: Effective tax/charge | B19: 0.025 | C19: 0.025 | D19: 0.025 | E19: % | F19: وفق هيكل الشركة | G19: اختياري
A20: Remaining economic life | B20: 10 | C20: 10 | D20: 10 | E20: سنة | F20: أفق الدراسة المالية المعتمدة 10 سنوات | G20: أقل من مدة حماية النموذج الصناعي البالغة 15 سنة
A21: Long-term revenue growth | B21: 0 | C21: 0.03 | D21: 0.05 | E21: % | F21: توقع مدعوم | G21: بعد السنة الخامسة
A22: Commercialization realization factor | B22: 0.45 | C22: 0.6 | D22: 0.75 | E22: % | F22: افتراض تقييمي لأركان – مرحلة ما قبل التشغيل | G22: يعكس أن تحقيق الإيرادات يتطلب تمويل المستثمر والتنفيذ التجاري؛ ليس Benchmark سوقيًا مباشرًا
A24: السنة | B24: 1 | C24: 2 | D24: 3 | E24: 4 | F24: 5 | G24: ملاحظة
A25: Revenue | B25: ='01 Stage1 Normalization'!B18 -> 15475200 | C25: ='01 Stage1 Normalization'!C18 -> 17022720 | D25: ='01 Stage1 Normalization'!D18 -> 18724992 | E25: ='01 Stage1 Normalization'!E18 -> 20597491 | F25: ='01 Stage1 Normalization'!F18 -> 22657240 | G25: مرتبط بالنموذج المالي الموحد
A27: السيناريو | B27: PV سنوات 1-5 | C27: PV سنوات 6-10 | D27: قيمة IP | E27: وزن | F27: قيمة مرجحة | G27: ملاحظة
A28: Low | B28: =SUM($B$25*$B$17*(1-$B$19)*$B$22/(1+$B$18)^1,$C$25*$B$17*(1-$B$19)*$B$22/(1+$B$18)^2,$D$25*$B$17*(1-$B$19)*$B$22/(1+$B$18)^3,$E$25*$B$17*(1-$B$19)*$B$22/(1+$B$18)^4,$F$25*$B$17*(1-$B$19)*$B$22/(1+$B$18)^5) -> 685955.11 | C28: =IF($B$20<=5,0,SUM(IF($B$20>=6,$F$25*(1+$B$21)^1*$B$17*(1-$B$19)*$B$22/(1+$B$18)^6,0),IF($B$20>=7,$F$25*(1+$B$21)^2*$B$17*(1-$B$19)*$B$22/(1+$B$18)^7,0),IF($B$20>=8,$F$25*(1+$B$21)^3*$B$17*(1-$B$19)*$B$22/(1+$B$18)^8,0),IF($B$20>=9,$F$25*(1+$B$21)^4*$B$17*(1-$B$19)*$B$22/(1+$B$18)^9,0),IF($B$20>=10,$F$25*(1+$B$21)^5*$B$17*(1-$B$19)*$B$22/(1+$B$18)^10,0))) -> 315983.66 | D28: =B28+C28 -> 1001938.8 | E28: 0.25 | F28: =D28*E28 -> 250484.69 | G28: مدخلات Low
A29: Base | B29: =SUM($B$25*$C$17*(1-$C$19)*$C$22/(1+$C$18)^1,$C$25*$C$17*(1-$C$19)*$C$22/(1+$C$18)^2,$D$25*$C$17*(1-$C$19)*$C$22/(1+$C$18)^3,$E$25*$C$17*(1-$C$19)*$C$22/(1+$C$18)^4,$F$25*$C$17*(1-$C$19)*$C$22/(1+$C$18)^5) -> 1277457.4 | C29: =IF($C$20<=5,0,SUM(IF($C$20>=6,$F$25*(1+$C$21)^1*$C$17*(1-$C$19)*$C$22/(1+$C$18)^6,0),IF($C$20>=7,$F$25*(1+$C$21)^2*$C$17*(1-$C$19)*$C$22/(1+$C$18)^7,0),IF($C$20>=8,$F$25*(1+$C$21)^3*$C$17*(1-$C$19)*$C$22/(1+$C$18)^8,0),IF($C$20>=9,$F$25*(1+$C$21)^4*$C$17*(1-$C$19)*$C$22/(1+$C$18)^9,0),IF($C$20>=10,$F$25*(1+$C$21)^5*$C$17*(1-$C$19)*$C$22/(1+$C$18)^10,0))) -> 689507.03 | D29: =B29+C29 -> 1966964.4 | E29: 0.5 | F29: =D29*E29 -> 983482.21 | G29: مدخلات Base
A30: High | B30: =SUM($B$25*$D$17*(1-$D$19)*$D$22/(1+$D$18)^1,$C$25*$D$17*(1-$D$19)*$D$22/(1+$D$18)^2,$D$25*$D$17*(1-$D$19)*$D$22/(1+$D$18)^3,$E$25*$D$17*(1-$D$19)*$D$22/(1+$D$18)^4,$F$25*$D$17*(1-$D$19)*$D$22/(1+$D$18)^5) -> 2093725.3 | C30: =IF($D$20<=5,0,SUM(IF($D$20>=6,$F$25*(1+$D$21)^1*$D$17*(1-$D$19)*$D$22/(1+$D$18)^6,0),IF($D$20>=7,$F$25*(1+$D$21)^2*$D$17*(1-$D$19)*$D$22/(1+$D$18)^7,0),IF($D$20>=8,$F$25*(1+$D$21)^3*$D$17*(1-$D$19)*$D$22/(1+$D$18)^8,0),IF($D$20>=9,$F$25*(1+$D$21)^4*$D$17*(1-$D$19)*$D$22/(1+$D$18)^9,0),IF($D$20>=10,$F$25*(1+$D$21)^5*$D$17*(1-$D$19)*$D$22/(1+$D$18)^10,0))) -> 1293077.1 | D30: =B30+C30 -> 3386802.5 | E30: 0.25 | F30: =D30*E30 -> 846700.62 | G30: مدخلات High
A32: 3) اختيار نطاق قيمة الملكية الفكرية
A33: المنهج | B33: Low | C33: Base | D33: High | E33: وزن Base | F33: قيمة مرجحة | G33: ملاحظة
A34: Cost Approach | B34: =($F$13-$F$11)+2062500*'03b Benchmark Evidence'!B17 -> 371250 | C34: =($F$13-$F$11)+2062500*'03b Benchmark Evidence'!C17 -> 412500 | D34: =($F$13-$F$11)+2062500*'03b Benchmark Evidence'!D17 -> 453750 | E34: 0.25 | F34: =C34*E34 -> 103125 | G34: Cross-check
A35: Relief from Royalty | B35: =$D$28 -> 1001938.8 | C35: =$D$29 -> 1966964.4 | D35: =$D$30 -> 3386802.5 | E35: 0.75 | F35: =C35*E35 -> 1475223.3 | G35: Income-led
A37: القيمة المختارة للـIP | B37: =MIN(B34:B35) -> 371250 | C37: =SUM(F34:F35) -> 1578348.3 | D37: =MAX(D34:D35) -> 3386802.5

Sheet 04 Founder Contribution
A1: المرحلة الثانية (ج) – تقييم مساهمة الشريك المؤسس
A3: المكون | B3: Low | C3: Base | D3: High | E3: عامل الإثبات | F3: عامل الازدواج | G3: Base معترف بها | H3: أسهم الآن؟ | I3: ملاحظات
A4: الملكية الفكرية / IP | B4: ='03 IP Valuation'!B37 -> 371250 | C4: ='03 IP Valuation'!C37 -> 1578348.3 | D4: ='03 IP Valuation'!D37 -> 3386802.5 | E4: 1 | F4: 0 | G4: =C4*E4*(1-F4) -> 1578348.3 | H4: نعم | I4: مرتبط بورقة IP
A5: مصاريف سابقة موثقة | B5: 0 | C5: 0 | D5: 0 | E5: 1 | F5: 0 | G5: =C5*E5*(1-F5) -> 0 | H5: نعم | I5: لا تُدرج مصروفات تأسيس ضمن مساهمة وسام إلا بقدر ما يثبت أنه تحمله شخصيًا؛ مبلغ 200,250 ريال في الدراسة المالية هو تكلفة مشروع وليس دليلاً على دفعه من وسام.
A6: Know-how منفصل | B6: 0 | C6: 0 | D6: 0 | E6: 0.75 | F6: 0.25 | G6: =C6*E6*(1-F6) -> 0 | H6: نعم – ضمن ملكية وسام | I6: الـKnow-how مملوك لوسام ومحتسب داخل حزمة الـIP. السيرة المهنية تدعم خبرة +20 سنة وخبرة مباشرة في الحجر الصناعي والقوالب؛ تستخدم لتعزيز الإثبات ولا تُسعّر منفصلة.
A7: تصميمات الماكينات/التطوير الهندسي | B7: 0 | C7: 0 | D7: 0 | E7: 1 | F7: 0 | G7: =C7*E7*(1-F7) -> 0 | H7: نعم – ملكية وسام | I7: التطوير الهندسي مملوك لوسام؛ السيرة المهنية تنسب إليه تصميم الخط الصناعي المؤتمت، ما يقوي الـCost cross-check. لا يضاف مرة ثانية فوق قيمة الـIP المختارة.
A8: علاقات/فرص مثبتة | B8: 0 | C8: 0 | D8: 0 | E8: 0.5 | F8: 0.5 | G8: =C8*E8*(1-F8) -> 0 | H8: بحذر | I8: تحتاج LOI/عقود أو دليل منفعة قابلة للقياس.
A9: جهد تأسيس سابق | B9: 30000 | C9: 60000 | D9: 90000 | E9: 0 | F9: 0.25 | G9: =C9*E9*(1-F9) -> 0 | H9: حسب الاتفاق | I9: لا يدخل في القيمة الحالية دون إثبات مستقل؛ ولا يُحتسب إذا كان متداخلاً مع الـKnow-how/التطوير الفني.
A10: أخرى | B10: 0 | C10: 0 | D10: 0 | E10: 1 | F10: 0 | G10: =C10*E10*(1-F10) -> 0 | H10: حسب الحالة
A12: إجمالي قيمة مساهمة المؤسس الحالية (Base) | G12: =SUM(G4:G10) -> 1578348.3
A14: المساهمة المستقبلية – منفصلة عن القيمة الحالية
A15: الدور المستقبلي | B15: مدة (سنة) | C15: قيمة سوقية سنوية | D15: تعويض نقدي سنوي | E15: خدمة غير مدفوعة | F15: عامل تنفيذ | G15: Earn-in Value | H15: آلية | I15: ملاحظات
A16: إدارة/تشغيل المصنع | B16: 2 | C16: 240000 | D16: 120000 | E16: =MAX(0,B16*(C16-D16)) -> 240000 | F16: 1 | G16: =E16*F16 -> 240000 | H16: راتب/حافز أداء – لا يدخل في الملكية الحالية | I16: قيمة مرجعية لخدمة مستقبلية فقط؛ لا تمنح أسهماً تلقائياً ولا تُخفض حصة المستثمر. أي أسهم مستقبلية تتطلب اتفاقاً مستقلاً ومؤشرات أداء.
A17: الإشراف الفني ونقل المعرفة | B17: 0 | C17: 0 | D17: 0 | E17: =MAX(0,B17*(C17-D17)) -> 0 | F17: 1 | G17: =E17*F17 -> 0 | H17: ضمن التعويض التشغيلي | I17: لا يضاف كأصل مستقل ما دام ضمن الإدارة/نقل المعرفة لتجنب الازدواج.
A18: تطوير المنتج | B18: 0 | C18: 0 | D18: 0 | E18: =MAX(0,B18*(C18-D18)) -> 0 | F18: 1 | G18: =E18*F18 -> 0 | H18: Milestone Equity
A19: أخرى | B19: 0 | C19: 0 | D19: 0 | E19: =MAX(0,B19*(C19-D19)) -> 0 | F19: 1 | G19: =E19*F19 -> 0 | H19: حسب الاتفاق
A21: إجمالي قيمة المساهمة المستقبلية المحتملة | G21: 240000 | H21: قيمة خدمة مستقبلية مرجعية فقط | I21: لا تدخل في Cap Table الحالي
A23: نطاق مساهمة المؤسس الحالية – لا يشمل الخدمات المستقبلية
B24: Low | C24: Base | D24: High
A25: Founder Current Contribution | B25: =B4 -> 371250 | C25: =G12 -> 1578348.3 | D25: =D4 -> 3386802.5

Sheet 05 Partnership Structure
A1: المرحلة الثالثة – تحديد هيكل الشراكة ونسب الملكية
A3: 1) مدخلات الشراكة | J3: مقارنة هيكل الملكية حسب السيناريو
A4: المدخل | B4: Low | C4: Base | D4: High | E4: الوحدة | F4: ملاحظة | M4: وسام | P4: المستثمر
A5: قيمة مساهمة المؤسس الحالية | B5: ='04 Founder Contribution'!B25 -> 371250 | C5: ='04 Founder Contribution'!C25 -> 1578348.3 | D5: ='04 Founder Contribution'!D25 -> 3386802.5 | E5: ريال | F5: مرتبطة بالمرحلة الثانية | J5: السيناريو | K5: وسام % | L5: المستثمر % | M5: وسام | Q5: المستثمر
A6: مساهمة المستثمر النقدية | B6: 5535983 | C6: 5535983 | D6: 5535983 | E6: ريال | F6: وفق إجمالي رأس المال المطلوب في الدراسة المالية المعتمدة | J6: Low | K6: 0.062846683 | L6: 0.93715332
A7: مساهمة المستثمر غير النقدية | B7: 0 | C7: 0 | D7: 0 | E7: ريال | F7: إن وجدت | J7: Base | K7: 0.22185477 | L7: 0.77814523
A8: تعديل تفاوضي للمؤسس | B8: 0 | C8: 0 | D8: 0 | E8: نقاط % | F8: إضافة/خصم مبرر بعد القيمة الاقتصادية | J8: High | K8: 0.37956785 | L8: 0.62043215
A9: Equity Pool / ESOP | B9: 0 | C9: 0 | D9: 0 | E9: % | F9: اختياري
J10: وسام | L10: المستثمر
A11: 2) النسبة الاقتصادية البحتة – قبل التفاوض
A12: السيناريو | B12: Founder Value | C12: Investor Value | D12: Total | E12: Founder % | F12: Investor % | G12: ملاحظة
A13: Conservative / Low | B13: =B5 -> 371250 | C13: =B6+B7 -> 5535983 | D13: =B13+C13 -> 5907233 | E13: =IF(D13=0,0,B13/D13) -> 0.062846683 | F13: =1-E13 -> 0.93715332 | G13: قيمة مؤسس منخفضة
A14: Base | B14: =C5 -> 1578348.3 | C14: =C6+C7 -> 5535983 | D14: =B14+C14 -> 7114331.3 | E14: =IF(D14=0,0,B14/D14) -> 0.22185477 | F14: =1-E14 -> 0.77814523 | G14: السيناريو الأساسي
A15: Upside / High | B15: =D5 -> 3386802.5 | C15: =D6+D7 -> 5535983 | D15: =B15+C15 -> 8922785.5 | E15: =IF(D15=0,0,B15/D15) -> 0.37956785 | F15: =1-E15 -> 0.62043215 | G15: قيمة مؤسس مرتفعة
A17: 3) المؤشر الاقتصادي للملكية عند التأسيس – قبل التفاوض التعاقدي
A18: السيناريو | B18: قيمة وسام العينية | C18: نقد المستثمر | D18: إجمالي القيمة عند التأسيس | E18: وسام % | F18: المستثمر % | G18: الخدمات المستقبلية | H18: ملاحظة
A19: Low | B19: =B13 -> 371250 | C19: =C13 -> 5535983 | D19: =B19+C19 -> 5907233 | E19: =B19/D19 -> 0.062846683 | F19: =C19/D19 -> 0.93715332 | G19: خارج الملكية الحالية | H19: المستثمر يمول 100% من الاحتياج النقدي
A20: Base | B20: =B14 -> 1578348.3 | C20: =C14 -> 5535983 | D20: =B20+C20 -> 7114331.3 | E20: =B20/D20 -> 0.22185477 | F20: =C20/D20 -> 0.77814523 | G20: خارج الملكية الحالية | H20: السيناريو المرجعي
A21: High | B21: =B15 -> 3386802.5 | C21: =C15 -> 5535983 | D21: =B21+C21 -> 8922785.5 | E21: =B21/D21 -> 0.37956785 | F21: =C21/D21 -> 0.62043215 | G21: خارج الملكية الحالية | H21: حد تقييم مرتفع للـIP وليس توصية تلقائية
A23: 4) التوصية الاستشارية
A24: المؤشر | B24: النتيجة | C24: الوحدة | D24: التفسير
A25: حصة وسام Base | B25: =E20 -> 0.22185477 | C25: % | D25: مؤشر اقتصادي بعد تعديل مخاطر التحول التجاري؛ لا يمثل حصة واجبة عند التأسيس
A26: حصة المستثمر Base | B26: =F20 -> 0.77814523 | C26: % | D26: المستثمر يمول كامل الاحتياج النقدي ويتحمل مخاطر التمويل والتنفيذ والتشغيل
A27: نطاق التقييم الاقتصادي لوسام | B27: =TEXT(E19,"0.0%")&" – "&TEXT(E21,"0.0%") -> 6.3% – 38.0% | C27: % | D27: Low–High كاختبار حساسية لقيمة الأصل، وليس نطاق تفاوض ملزم
A28: الخدمات المستقبلية | B28: لا تدخل في Cap Table الحالي | D28: تعالج براتب/حافز أداء أو Earn-in مشروط بنتائج فعلية؛ لا تمنح مقدماً.
A29: قاعدة التفاوض | B29: عدم التحويل الآلي للتقييم إلى أسهم | D29: قيمة الـIP مؤشر تفاوضي فقط. عند التأسيس يراعى أن المستثمر يضخ 100% من النقد وأن جزءاً من منفعة الـIP لن يتحقق إلا بعد التمويل والتنفيذ التجاري.
A32: ضوابط مقترحة لحماية التمويل النقدي عند التفاوض
A33: الضابط | B33: المعالجة | C33: الهدف | D33: الحالة
A34: نقل حقوق الـIP | B34: توثيق الحقوق المنقولة/المرخصة للشركة قبل تثبيت المقابل | C34: ربط الحصة بأصل قابل للاستغلال | D34: أساسي
A35: الملكية عند التأسيس | B35: لا تُستمد آلياً من قيمة التقييم وحدها | C35: مراعاة أن المستثمر يمول 100% من الاحتياج النقدي | D35: تفاوضي
A36: أي حصة إضافية مستقبلية | B36: Earn-in / Vesting مرتبط بمراحل تشغيل وإنتاج/مبيعات متفق عليها | C36: عدم دفع قيمة النجاح قبل تحققه | D36: مشروط
A37: الخدمات المستقبلية | B37: راتب/حافز أداء منفصل عن الملكية الحالية | C37: منع تحميل المستثمر قيمة خدمة لم تُنفذ بعد | D37: منفصل
A38: ملاحظة: النسب النهائية وشروط نقل الحقوق والـVesting تُحسم تعاقدياً بين الأطراف، ويُراجع الشكل النظامي النهائي قبل التوثيق.

Sheet 06 Client Output
A1: ملخص النتائج – للاستخدام في التقرير/العرض على العميل
A3: أولاً: المرحلة الثانية – تقييم مساهمة المؤسس
A4: المؤشر | B4: Low | C4: Base | D4: High
A5: قيمة الملكية الفكرية | B5: ='03 IP Valuation'!B37 -> 371250 | C5: ='03 IP Valuation'!C37 -> 1578348.3 | D5: ='03 IP Valuation'!D37 -> 3386802.5
A6: إجمالي مساهمة المؤسس الحالية | B6: ='04 Founder Contribution'!B25 -> 371250 | C6: ='04 Founder Contribution'!C25 -> 1578348.3 | D6: ='04 Founder Contribution'!D25 -> 3386802.5
A7: المساهمة المستقبلية المحتملة | B7: ='04 Founder Contribution'!G21 -> 240000 | C7: ='04 Founder Contribution'!G21 -> 240000 | D7: ='04 Founder Contribution'!G21 -> 240000
A8: ملاحظة | B8: نطاق محافظ | C8: المرجع الرئيسي | D8: ليس سقفًا تفاوضيًا تلقائيًا
A10: ثانياً: المؤشر الاقتصادي للملكية – قبل التفاوض التعاقدي
A11: السيناريو | B11: قيمة وسام العينية | C11: نقد المستثمر | D11: حصة وسام | E11: حصة المستثمر
A12: Low | B12: ='05 Partnership Structure'!B19 -> 371250 | C12: ='05 Partnership Structure'!C19 -> 5535983 | D12: ='05 Partnership Structure'!E19 -> 0.062846683 | E12: ='05 Partnership Structure'!F19 -> 0.93715332
A13: Base | B13: ='05 Partnership Structure'!B20 -> 1578348.3 | C13: ='05 Partnership Structure'!C20 -> 5535983 | D13: ='05 Partnership Structure'!E20 -> 0.22185477 | E13: ='05 Partnership Structure'!F20 -> 0.77814523
A14: High | B14: ='05 Partnership Structure'!B21 -> 3386802.5 | C14: ='05 Partnership Structure'!C21 -> 5535983 | D14: ='05 Partnership Structure'!E21 -> 0.37956785 | E14: ='05 Partnership Structure'!F21 -> 0.62043215
A15: التوصية | B15: Base مؤشر اقتصادي مرجعي بعد خصم مخاطر التحول التجاري، وليس نسبة أسهم واجبة. المستثمر يمول كامل الاحتياج النقدي؛ لذلك يُنصح بعدم تحويل قيمة الـIP آلياً إلى ملكية مقدماً، وفصل أي قيمة مستقبلية في Earn-in مشروط.
A17: ثالثاً: معالجة دور وسام المستقبلي
A18: المبدأ | B18: الإدارة والتشغيل ونقل المعرفة بعد التأسيس لا تُضاف تلقائياً إلى ملكية وسام الحالية.
A19: المقابل المقترح | B19: راتب سوقي/راتب مخفض + حافز أداء. وإذا اتفق الطرفان على Earn-in فيكون منفصلاً ومشروطاً بـVesting وKPIs وموافقة المستثمر.
A20: لماذا؟ | B20: لأن المستثمر يضخ 5,535,983 ريال نقداً ويتحمل مخاطر التنفيذ والتشغيل والسوق، بينما مساهمة أ. وسام غير نقدية؛ لذلك أضيف عامل تحقق تجاري على Income Approach وفُصلت الخدمات المستقبلية عن الملكية الحالية.
A21: منع الازدواج | B21: لا نضيف الخبرة الشخصية أو تصميم الخط أو Know-how مرة ثانية إذا كانت منفعتها محسوبة بالفعل داخل قيمة الـIP المختارة.
A22: الخلاصة | B22: Cap Table الاقتصادي يعرض مقارنة مرجعية فقط. نسبة التأسيس النهائية لا تُستنتج آلياً من التقييم، ويمكن حماية المستثمر عبر نقل الحقوق أولاً وEarn-in/Vesting لأي قيمة مستقبلية.
A23: ملاحظة التقييم | B23: تم احتساب هيكل الملكية الحالي على أساس التمويل النقدي للمستثمر والقيمة العينية الحالية لأ. وسام فقط، مع فصل الخدمات المستقبلية عن الملكية الحالية.
A24: استكمال الأدلة
A25: تُراجع البنود الموضحة في شيت «07 استكمال بيانات وسام» عند توفر مستندات إضافية، وقد تدعم التقييم أو تعدله وفق أثرها وبعد منع الازدواج.

Sheet 03b Benchmark Evidence
A1: المراجع المقارنة والأدلة الداعمة للتقييم
A3: المحور | B3: المقارنة | C3: المعدل/النطاق | D3: كيفية الاستخدام | E3: درجة الملاءمة | F3: المصدر
A4: Royalty | B4: Technology license – SEC filing | C4: 3% Net Sales | D4: Low case | E4: متوسط – تقنية مرخصة وليست حجر صناعي | F4: https://www.sec.gov/Archives/edgar/data/1376339/000119312508024469/dex1032.htm
A5: Royalty | B5: Exclusive patent/manufacturing license – SEC filing | C5: 4% Net Sales | D5: Base anchor | E5: متوسط – تصنيع/براءة | F5: https://www.sec.gov/Archives/edgar/data/75439/000095013708005016/c25377exv10w50.htm
A6: Royalty | B6: Patent + Know-how license – SEC filing | C6: 4.5% Net Sales | D6: يدعم Base/High | E6: جيد نسبيًا – يشمل Know-how + patent | F6: https://www.sec.gov/Archives/edgar/data/1277576/000100201407000720/exh1021.htm
A7: Royalty | B7: Licensed technology including know-how/trade secrets – SEC filing | C7: 5% Net Selling Price | D7: High case | E7: جيد نسبيًا – technology + know-how | F7: https://www.sec.gov/Archives/edgar/data/1289047/000108671505000023/exhibit1014exclusivetechnolo.htm
A8: Royalty | B8: Patent/know-how licensed product – SEC filing | C8: 5% Net Sales | D8: High cross-check | E8: جيد نسبيًا – know-how explicitly included | F8: https://www.sec.gov/Archives/edgar/data/720154/000114420407052871/v089521_ex10-3.htm
A9: Methodology | B9: WIPO IP valuation | C9: Income / Market / Cost | D9: Framework | E9: عالي – مرجع منهجي | F9: https://www.wipo.int/en/web/business/ip-valuation
A10: Methodology | B10: WIPO Cost Method | C10: Creation / Replacement / Reproduction cost | D10: Cost cross-check | E10: عالي – مرجع منهجي | F10: https://www.wipo.int/web-publications/intellectual-property-valuation-basics-for-technology-transfer-professionals/en/4-the-cost-method.html
A11: Engineering | B11: Custom automated manufacturing equipment NRE/design | C11: 18%-22% of total project/equipment budget | D11: اختبار استرشادي لتكلفة التطوير الهندسي | E11: مرجع استرشادي ثانوي – لا يستخدم منفرداً لتحديد القيمة | F11: افتراض استرشادي لأركان لاختبار تكلفة التطوير فقط؛ ليس عرض سعر أو تكلفة فعلية مثبتة
A13: خلاصة تطبيق الـBenchmark
A14: البند | B14: Low | C14: Base | D14: High | E14: قرار النموذج | F14: ملاحظة
A15: Royalty Rate | B15: 0.03 | C15: 0.04 | D15: 0.05 | E15: يطبق على الإيرادات | F15: النطاق مدعوم بمعاملات ترخيص منشورة، مع مراعاة عدم وجود Comparable مطابق تماماً لنشاط المشروع.
A16: Discount Rate | B16: 0.22 | C16: 0.2 | D16: 0.18 | E16: افتراض مخاطر | F16: افتراض تقييمي داخلي يعكس مخاطر الأصل والمشروع؛ ليس Benchmark سوقيًا مباشرًا
A17: Engineering Design % | B17: 0.18 | C17: 0.2 | D17: 0.22 | E17: Cross-check استرشادي فقط | F17: لا يضاف فوق Income Approach لمنع Double Counting
A18: Engineering Design Value | B18: 371250 | C18: 412500 | D18: 453750 | E18: ضمن Cost Approach | F18: على تكلفة خط 2,062,500 ريال
A20: أدلة داعمة خاصة بوسام
A21: الدليل | B21: ما الذي يدعمه؟ | C21: أثره على التقييم | D21: هل يضيف قيمة مستقلة؟ | E21: درجة الاستخدام | F21: ملاحظة
A22: السيرة المهنية – خبرة +20 سنة | B22: Know-how / خبرة تطبيقية في العمارة والتشطيبات والحجر الصناعي والقوالب | C22: يرفع قوة الإثبات النوعي للـKnow-how | D22: لا | E22: داعم | F22: لا نحول سنوات الخبرة إلى مبلغ مستقل لتجنب Double Counting
A23: السيرة المهنية – وصف الابتكار والحماية التركية 2024/007051 | B23: إسناد الابتكار والحماية إلى وسام | C23: يدعم ملكية/إسناد حزمة IP؛ المطابقة النهائية مع مستند التسجيل عند توفره | D23: لا | E23: داعم | F23: يستخدم كدليل داعم، وتظل شهادة الحماية السعودية مستند الإثبات المباشر المتاح ضمن ملف التقييم.
A24: السيرة المهنية – تصميم الخط الصناعي المؤتمت | B24: إسناد التطوير الهندسي/تصميم الخط إلى وسام | C24: يقوي استخدام Engineering benchmark كـCost cross-check | D24: لا | E24: داعم | F24: لا يضاف فوق Relief-from-Royalty

Sheet 07 استكمال بيانات وسام
A1: بيانات ومستندات استكمال التقييم – أ. وسام
A2: يرجى استكمال ما يتوافر من البيانات والمستندات أدناه. لا يُطلب من أ. وسام تحديد قيمة الـKnow-how أو نسبة الشراكة نقوم نحن بمراجعة أثر أي معلومات إضافية على التقييم.
A4: البند المطلوب من وسام | B4: ما المطلوب تعبئته/إرفاقه | C4: الحالة الحالية | D4: هل يؤثر على التقييم؟ | E4: أين ينعكس في النموذج؟ | F4: ملاحظات / مستندات مرفقة
A5: تطوير الخلطة والتجارب | B5: القيمة الفعلية التي تحملها شخصياً + فواتير/تحويلات/سجلات تجارب إن وجدت | C5: مطلوب إن وجد | D5: نعم – Cost Approach | E5: 03 IP Valuation
A6: النماذج الأولية | B6: التكلفة الفعلية المدفوعة شخصياً + صور/فواتير/إثبات تنفيذ | C6: مطلوب إن وجد | D6: نعم – Cost Approach | E6: 03 IP Valuation
A7: القوالب والتصميمات | B7: ما تم تصميمه/تنفيذه بواسطة وسام، والتكلفة التي تحملها شخصياً، مع الرسومات أو الفواتير إن وجدت | C7: مطلوب إن وجد | D7: نعم – Cost Approach | E7: 03 IP Valuation / 02 IP Inventory
A8: الاختبارات والشهادات الفنية | B8: اسم الاختبار/الجهة/التاريخ/القيمة المدفوعة شخصياً + المستند | C8: مطلوب إن وجد | D8: نعم – Cost Approach | E8: 03 IP Valuation
A9: رسوم الحماية السعودية | B9: إثبات ما دفعه وسام شخصياً من رسوم تسجيل/إيداع/استشارات | C9: مطلوب للتكلفة فقط | D9: نعم – التكلفة فقط؛ الملكية معتمدة | E9: 03 IP Valuation
A10: رسوم الحماية التركية | B10: إثبات الرسوم المدفوعة شخصياً + مستند التسجيل/الملكية | C10: مطلوب للتكلفة فقط | D10: نعم – التكلفة فقط؛ الملكية معتمدة وفق أساس العمل | E10: 03 IP Valuation / 02 IP Inventory
A11: تصميم خط الإنتاج والتعديلات الهندسية | B11: وصف مختصر لما صممه أو عدله وسام بنفسه + رسومات/مخططات/مراسلات مع المصنع أو المورد إن وجدت | C11: مطلوب لتعزيز الإثبات | D11: نعم – يقوي Benchmark ولا يضاف مرتين | E11: 03 IP Valuation
A12: ساعات/جهد التطوير السابق | B12: تقدير عدد الساعات أو الأشهر الفعلية قبل التأسيس، مع وصف الأعمال والفترة | C12: اختياري إذا أمكن إثباته | D12: قد يؤثر – بعد فحص الازدواج | E12: 03 IP Valuation / 04 Founder Contribution
A13: مصاريف سابقة أخرى دفعها وسام | B13: بيان المصروف، التاريخ، القيمة، سبب الصرف، وإثبات الدفع | C13: مطلوب إن وجدت | D13: نعم فقط إذا دفعها شخصياً ولم تُحتسب سابقاً | E13: 04 Founder Contribution
A14: عقود / LOI / فرص تجارية مرتبطة بوسام | B14: اسم الجهة، نوع الالتزام، القيمة المتوقعة، مدة الاتفاق، والمستند الداعم | C14: اختياري | D14: فقط إذا كانت منفعة قابلة للقياس والتحويل للشركة | E14: 04 Founder Contribution
A15: حقوق أو تصميمات أخرى ستُنقل للشركة | B15: وصف الحق، مالكه، رقم التسجيل إن وجد، ونطاق النقل/الترخيص للشركة | C15: مطلوب إن وجدت | D15: نعم بعد تقييم مستقل ومنع الازدواج | E15: 02 IP Inventory
A17: بنود لا يُطلب من وسام تسعيرها بنفسه
A18: Know-how والخبرة المهنية | B18: لا يضع وسام قيمة مالية؛ يتم تقييمها استشارياً وتستخدم خبرته كدليل داعم. | C18: لا يحتاج تعبئة قيمة | D18: محسوبة ضمن حزمة IP وفق النموذج | E18: 03 IP Valuation / 04 Founder Contribution
A19: نسبة الشراكة | B19: لا يضع وسام نسبة في هذا الشيت؛ النسبة تنتج من التقييم ثم تُناقش تفاوضياً. | C19: لا يحتاج تعبئة | D19: ناتج وليس Input | E19: 05 Partnership Structure
A20: الإدارة والتشغيل المستقبلي | B20: لا تدخل تلقائياً في الملكية الحالية. أي راتب/حافز/Earn-in يتم الاتفاق عليه منفصلاً. | C20: يحدد لاحقاً باتفاق الطرفين | D20: لا يؤثر على Cap Table الحالي | E20: 04 Founder Contribution / 05 Partnership Structure

Sheet 00 الغلاف والملخص التنفيذي
A1: أركان للاستشارات ودراسات الجدوى
A4: التقييم الاقتصادي لمساهمة أ. وسام وهيكل الشراكة المقترح
A6: مشروع مصنع الحجر الصناعي – الترفنتينو | تقرير التقييم الاقتصادي
A8: الملخص التنفيذي
A9: المؤشر | B9: النتيجة | D9: البيان | E9: Low | F9: Base | G9: High | H9: ملاحظة
A10: الاحتياج النقدي للمشروع (ريال) | B10: 5535983 | D10: قيمة مساهمة وسام (ريال) | E10: ='04 Founder Contribution'!B25 -> 371250 | F10: ='04 Founder Contribution'!C25 -> 1578348.3 | G10: ='04 Founder Contribution'!D25 -> 3386802.5 | H10: حساسية لقيمة الأصل غير النقدي
A11: قيمة مساهمة وسام – Base (ريال) | B11: ='04 Founder Contribution'!C25 -> 1578348.3 | D11: حصة وسام | E11: ='05 Partnership Structure'!E19 -> 0.062846683 | F11: ='05 Partnership Structure'!E20 -> 0.22185477 | G11: ='05 Partnership Structure'!E21 -> 0.37956785 | H11: مؤشرات اقتصادية وليست نسب ملكية واجبة
A12: إجمالي القيمة عند التأسيس – Base (ريال) | B12: ='05 Partnership Structure'!D20 -> 7114331.3 | D12: حصة المستثمر | E12: ='05 Partnership Structure'!F19 -> 0.93715332 | F12: ='05 Partnership Structure'!F20 -> 0.77814523 | G12: ='05 Partnership Structure'!F21 -> 0.62043215 | H12: المستثمر يمول كامل الاحتياج النقدي
A13: مؤشر ملكية وسام الاقتصادي | B13: ='05 Partnership Structure'!E20 -> 0.22185477 | D13: الخدمات المستقبلية | E13: خارج الملكية الحالية | F13: خارج الملكية الحالية | G13: خارج الملكية الحالية | H13: راتب/حافز أو Earn-in باتفاق مستقل
A14: مؤشر ملكية المستثمر الاقتصادي | B14: ='05 Partnership Structure'!F20 -> 0.77814523 | D14: السيناريو المرجعي | E14: — | F14: Base | G14: — | H14: المرجع الاقتصادي بعد تعديل مخاطر ما قبل التشغيل
A15: طبيعة مساهمة المستثمر | B15: تمويل نقدي 100% من الاحتياج | D15: حالة High | E15: — | F15: — | G15: حد تقييم مرتفع | H15: ليس توصية ملكية تلقائية
A17: النتيجة الاستشارية
A18: وفق المدخلات الحالية، تم تعديل التقييم ليعكس أن المشروع في مرحلة ما قبل التشغيل وأن المستثمر يضخ كامل الاحتياج النقدي ويتحمل مخاطر التنفيذ والتشغيل والسوق. لذلك لا تُحوَّل قيمة مساهمة أ. وسام غير النقدية آلياً إلى نسبة ملكية واجبة، ويُستخدم السيناريو Base كمؤشر اقتصادي تفاوضي بعد تطبيق عامل تحقق تجاري، مع فصل أي خدمات أو قيمة مستقبلية في Earn-in/Vesting مشروط.
A22: حدود واعتمادات التقييم
A23: • المرجع المالي: الدراسة المالية المعتمدة منفصلة عن الدراسة الفنية/السوقية. • الفني والسوقي: الدراسة النهائية الفنية والتسويقية فقط. • ملكية IP/Know-how والتطوير الفني: معتمدة لوسام كأساس عمل التقييم. • الخبرة الشخصية لا تُسعّر كأصل مستقل إذا كانت منفعتها محسوبة ضمن حزمة IP/Know-how. • الخدمات المستقبلية لا تدخل في Cap Table الحالي تلقائياً.
A28: إعداد: أركان للاستشارات ودراسات الجدوى | تحليل اقتصادي استشاري لدعم التفاوض واتخاذ القرار
